mufasa/UltraCube.py
mufasa/__init__.py
mufasa/_metadata.py
mufasa/_version.py
mufasa/aic.py
mufasa/clean_fits.py
mufasa/convolve_tools.py
mufasa/deblend_cube.py
mufasa/exceptions.py
mufasa/guess_refine.py
mufasa/master_fitter.py
mufasa/moment_guess.py
mufasa/multi_v_fit.py
mufasa/signals.py
mufasa/slab_sort.py
mufasa/spec_models/BaseModel.py
mufasa/spec_models/HyperfineModel.py
mufasa/spec_models/SpecModels.py
mufasa/spec_models/__init__.py
mufasa/spec_models/ammonia_multiv.py
mufasa/spec_models/m_constants.py
mufasa/spec_models/meta_model.py
mufasa/spec_models/n2hp_constants.py
mufasa/spec_models/n2hp_deblended.py
mufasa/spec_models/n2hp_multiv.py
mufasa/spec_models/nh3_deblended.py
mufasa/utils/__init__.py
mufasa/utils/dataframe.py
mufasa/utils/decorators.py
mufasa/utils/fits_utils.py
mufasa/utils/interpolate.py
mufasa/utils/map_divide.py
mufasa/utils/memory.py
mufasa/utils/mufasa_log.py
mufasa/utils/multicore.py
mufasa/utils/neighbours.py
mufasa/visualization/__init__.py
mufasa/visualization/scatter_3D.py
mufasa/visualization/spec_viz.py
mufasa-1.5.0.dist-info/LICENSE
mufasa-1.5.0.dist-info/METADATA
mufasa-1.5.0.dist-info/WHEEL
mufasa-1.5.0.dist-info/top_level.txt
mufasa-1.5.0.dist-info/RECORD
